{
  "enableUIDisplayConfiguration": true,
  "uiDisplayConfigurations": {
	"loanAccount": {
	  "isHiddenField": {
		"fundId": false,
		"externalId": false,
		"linkAccountId": false,
		"createStandingInstruction": false,
		"numberOfRepayments": false,
		"repaymentEvery": false,
		"repaymentFrequencyType": false,
		"repaymentFrequencyNthDayType": false,
		"repaymentFrequencyDayOfWeekType": false,
		"interestChargedFromDate": false,
		"repaymentsStartingFromDate": false,
		"interestType": false,
		"amortizationType": false,
		"interestCalculationPeriodType": false,
		"inArrearsTolerance": false,
		"graceOnInterestCharged": false,
		"transactionProcessingStrategyId": false,
		"graceOnInterestPayment": false,
		"graceOnArrearsAgeing": false,
		"syncDisbursementDateWithMeeting": false,
		"recurringMoratoriumOnPrincipalPeriods": false,
		"brokenPeriodMethodType": false
	  },
	  "isMandatory": {
		"externalId": false,
		"repaymentsStartingFromDate": false,
		"loanPurposeId": false
	  },
	  "isHiddenSection": {
		"interestRecalculationSection": false,
		"collateralSection": false
	  },
	  "isShowField": {
		"nextRepaymentDateDisburseScreen": false,
		"adjustRepaymentDateDisburseScreen": false
	  },
	  "isReadOnlyField": {
		"loanTermFrequencyType": false,
		"interestChargedFromDate": false,
		"displayName": false,
		"interestRatePerPeriod": false,
		"loanPurposeId": false,
		"syncRepaymentsWithMeeting": false,
		"repaymentFrequencyType": false
	  },
	  "isAutoPopulate": {
		"interestChargedFromDate": false
	  },
	  "isDefaultValue": {
		"syncDisbursementWithMeeting": false,
		"considerFutureDisbursmentsInSchedule": true,
		"fundId": "",
		"paymentTypeId": ""
	  }
	},
	"viewLoanAccountDetails": {
	  "isHiddenFeild": {
		"viewReportButton": false,
		"editTranches": false,
		"term": false,
		"currency": false,
		"interestCompoundingPeriod": false,
		"interestCalculatedUsing": false,
		"lockinPeriodFrequency": false,
		"isMandatoryDepositCheckBox": false,
		"groupMeeting": false,
		"settings": false,
		"interestRateChat": false,
		"charges": false,
		"addCharges": false
	  }
	},
	"clientAccount": {
	  "isMandatory": {
		"externalId": true
	  }
	},
	"viewClient": {
	  "isHiddenField": {
		"pincode": false
	  	}
	},
	"collectionSheet": {
	  "isAutoPopulate": {
		"paymentTypeOption": true
	  },
	  "isHiddenFeild": {
		"newtransactionDate": false,
		"paymentDetails": false
	  }
	},
	"createClient": {
	  "isReadOnlyField": {
		"staff": false,
		"pincode": false,
		"active": false
	  },
	  "isValidateDOBField": {
		"active": false,
		"ageCriteria": {
		  "minAge": "",
		  "maxAge": ""
		}
	  },
	  "isHiddenField": {
		"hideClientClassification": false,
		"staff": false,
		"legalForm": false,
		"middleName": false,
		"externalId": false,
		"submittedOn": false,
		"openSavingsProduct": false
	  },
	  "isMandatoryField": {
		"dateOfBirth": false,
		"clientClassificationId": false,
		"externalId": false
	  }
	},
	"defaultGISConfig": {
	  "address": {
		"countryName": "",
		"stateName": "",
		"addressType": ""
	  },
	  "paymentType": {
		"expectedDisbursalPaymentType": "",
		"expectedRepaymentPaymentType": ""
	  },
	  "bankAccountDetails":{
		"bankName":""
	  },
	  "isReadOnlyField": {
		"countryName": false
	  }
	},
	"createCenter": {
	  "isReadOnlyField": {
		"active": false,
		"name": false
	  },
	  "isHiddenField": {
		"villageOptions": true,
		"showGroupExternalId" : true,
		"showSubmittedOn" : true,
		"showStaff" : true,
		"addclients" : true
	  }
	},
	"createGroup": {
	  "isReadOnlyField": {
		"staff": false,
		"active": false
	  },
	  "isAutoPopulate": {
		"active": false
	  },
	  "isMandatory":{
		"externalId":true
	  },
	  "isHiddenMenu": {
		"attachmeeting": true,
		"groupExternalId": false,
		"submittedOn": false,
		"staff": false,
		"addclients": false
	  }
	},
	"labelChanges": {
	  "calendarChagesEffectiveFrom": true
	},
	"createVillage": {
	  "isReadOnlyField": {
		"active": false
	  },
	  "isValidatePinCodeField": {
		"active": false,
		"pinCodeValues": {
		  "startDigit": {
			"Karnataka": "",
			"Maharashtra": ""
		  },
		  "pincodeLenght": ""
		}
	  },
	  "isHiddenField": {
		"villageCode": false
	  }
	},
	"clientIdentifier": {
	  "identitiesMatchLuhnsAlgorithm": {
		"clientIdentifierValidation": false
	  },
	  "hiddenFields": {
		"status": false
	  }
	},
	"reportParameterConfiguration": {
	  "datePicker": {
		"reportNames": "'Expected Payments By Date - Basic'",
		"restrictedDate": ""
	  }
	},
	"journalEntryConfiguration": {
	  "allowMultipleCreditAndDebitEntries": false
	},
	"bankAccountDetails": {
	  "isMandatory": {
		"bankAccountHolderName": true,
		"bankAccountNumber": true,
		"accountType": false,
		"bankIFSCCode": false,
		"bankName": false,
		"bankCity": false,
		"mobileNumber": false,
		"lastTransactionDate": false
	  },
	  "isHiddenField":{
		"lastTransactionDate": true
	  },
	  "regexValidations" :{
		"mobileNumber":"",
		"bankIFSCCode":""
	  }
	}
  }
 }
	